{"after":"Y3Vyc29yOnYyOpK0MjAyMy0wMi0xNlQyMjozMTowOVrOSivgnw==","repositories":[{"name":"facebook/react","stars":203483},{"name":"facebook/react-native","stars":108063},{"name":"vercel/next.js","stars":101995},{"name":"facebook/create-react-app","stars":99067},{"name":"mui/material-ui","stars":85011},{"name":"storybookjs/storybook","stars":77213},{"name":"sveltejs/svelte","stars":66128},{"name":"reduxjs/redux","stars":59308},{"name":"remix-run/react-router","stars":49785},{"name":"microsoft/playwright","stars":48408},{"name":"DefinitelyTyped/DefinitelyTyped","stars":43062},{"name":"babel/babel","stars":42007},{"name":"facebook/jest","stars":41568},{"name":"typescript-cheatsheets/react","stars":39869},{"name":"styled-components/styled-components","stars":38355},{"name":"TanStack/query","stars":33408},{"name":"JedWatson/react-select","stars":25844},{"name":"bvaughn/react-virtualized","stars":24720},{"name":"floating-ui/floating-ui","stars":24666},{"name":"reduxjs/react-redux","stars":22649},{"name":"remix-run/remix","stars":22559},{"name":"enzymejs/enzyme","stars":19963},{"name":"websockets/ws","stars":19527},{"name":"react-dnd/react-dnd","stars":18928},{"name":"jsdom/jsdom","stars":18531},{"name":"apollographql/apollo-client","stars":18531},{"name":"testing-library/react-testing-library","stars":17552},{"name":"less/less.js","stars":16896},{"name":"emotion-js/emotion","stars":16123},{"name":"tensorflow/tfjs-models","stars":12427},{"name":"codesandbox/codesandbox-client","stars":12243},{"name":"gaearon/react-hot-loader","stars":12242},{"name":"react-static/react-static","stars":10226},{"name":"FormidableLabs/victory","stars":10210},{"name":"reactjs/react-transition-group","stars":9699},{"name":"mongodb/node-mongodb-native","stars":9697},{"name":"reactjs/reactjs.org","stars":8737},{"name":"jsx-eslint/eslint-plugin-react","stars":8325},{"name":"adobe/react-spectrum","stars":8133},{"name":"facebook/hermes","stars":7746},{"name":"mdn/content","stars":7534},{"name":"final-form/react-final-form","stars":7219},{"name":"cssinjs/jss","stars":6912},{"name":"jquense/react-big-calendar","stars":6390},{"name":"yarnpkg/berry","stars":6077},{"name":"palantir/tslint","stars":5920},{"name":"changesets/changesets","stars":5558},{"name":"fkling/astexplorer","stars":5333},{"name":"dequelabs/axe-core","stars":4984},{"name":"microsoft/vscode-docs","stars":4919},{"name":"microsoft/TypeScript-Handbook","stars":4866},{"name":"import-js/eslint-plugin-import","stars":4636},{"name":"mdn/browser-compat-data","stars":4430},{"name":"oliviertassinari/react-swipeable-views","stars":4317},{"name":"seek-oss/playroom","stars":4258},{"name":"web-platform-tests/wpt","stars":4244},{"name":"testing-library/jest-dom","stars":3823},{"name":"mbrn/material-table","stars":3419},{"name":"reactjs/react-docgen","stars":3373},{"name":"testing-library/dom-testing-library","stars":3089},{"name":"jsx-eslint/eslint-plugin-jsx-a11y","stars":3077},{"name":"mjackson/unpkg","stars":2562},{"name":"mui/mui-x","stars":2482},{"name":"React95/React95","stars":2315},{"name":"mui/material-ui-pickers","stars":2314},{"name":"Openarl/PathOfBuilding","stars":2167},{"name":"webpack/webpack.js.org","stars":2165},{"name":"kentcdodds/kentcdodds.com","stars":1882},{"name":"microsoft/TypeScript-Website","stars":1811},{"name":"mridgway/hoist-non-react-statics","stars":1780},{"name":"pngwn/MDsveX","stars":1668},{"name":"WICG/focus-visible","stars":1588},{"name":"prettier/tslint-config-prettier","stars":1227},{"name":"styleguidist/react-docgen-typescript","stars":1037},{"name":"webcomponents/custom-elements-everywhere","stars":1025},{"name":"callstack/repack","stars":1002},{"name":"microsoft/dtslint","stars":918},{"name":"oliviertassinari/babel-plugin-transform-react-remove-prop-types","stars":896},{"name":"kentcdodds/kcd-scripts","stars":869},{"name":"arcanis/clipanion","stars":860},{"name":"oblador/react-native-performance","stars":783},{"name":"kentcdodds/old-kentcdodds.com","stars":732},{"name":"babel/website","stars":714},{"name":"circleci/circleci-docs","stars":711},{"name":"sveltejs/sapper-template","stars":709},{"name":"styled-components/styled-components-website","stars":575},{"name":"selfdefined/web-app","stars":570},{"name":"testing-library/svelte-testing-library","stars":542},{"name":"w3c/aria","stars":542},{"name":"microsoft/TypeScript-DOM-lib-generator","stars":506},{"name":"lexich/redux-api","stars":498},{"name":"fb55/css-select","stars":483},{"name":"timoxley/keycode","stars":436},{"name":"paularmstrong/build-tracker","stars":430},{"name":"microsoft/vscode-tslint","stars":407},{"name":"testing-library/testing-library-docs","stars":401},{"name":"microsoft/azure-devops-node-api","stars":400},{"name":"uber/react-vis-force","stars":393},{"name":"microsoft/types-publisher","stars":393},{"name":"tdeekens/flopflip","stars":386},{"name":"fullstackopen-2019/fullstackopen-2019.github.io","stars":342},{"name":"testing-library/eslint-plugin-jest-dom","stars":313},{"name":"cssinjs/theming","stars":299},{"name":"TheBrainFamily/wait-for-expect","stars":277},{"name":"babel-utils/babel-plugin-tester","stars":265},{"name":"microsoft/DefinitelyTyped-tools","stars":256},{"name":"sw-yx/swyxdotio","stars":241},{"name":"eps1lon/types-react-codemod","stars":235},{"name":"OmegaK2/PyPoE","stars":233},{"name":"A11yance/aria-query","stars":214},{"name":"fb55/css-what","stars":211},{"name":"TrySound/rollup-plugin-size-snapshot","stars":164},{"name":"jsdom/cssstyle","stars":84},{"name":"eps1lon/dom-accessibility-api","stars":67},{"name":"dperini/nwsapi","stars":59},{"name":"merceyz/typescript-to-proptypes","stars":51},{"name":"eps1lon/screen-reader-testing-library","stars":40},{"name":"mui/mui-public","stars":33},{"name":"marcelowa/promise-all-properties","stars":26},{"name":"eps1lon/actions-label-merge-conflict","stars":25},{"name":"arcanis/jest-pnp-resolver","stars":23},{"name":"joehillen/ev-fish","stars":17},{"name":"Chuanhsing/poe-api","stars":15},{"name":"eps1lon/poe-recraft","stars":11},{"name":"Uclusion/uclusion_web_ui","stars":11},{"name":"eps1lon/material-ui-playroom","stars":10},{"name":"eps1lon/poe-db","stars":5},{"name":"eps1lon/dependabot-clickable-commands","stars":5},{"name":"eps1lon/mui-scripts-incubator","stars":4},{"name":"dmtrKovalenko/CV","stars":3},{"name":"yarnplugins/yarn-plugin-deduplicate","stars":3},{"name":"eps1lon/solverfox.dev","stars":3},{"name":"testing-library/web-testing-library","stars":3},{"name":"eps1lon/test262-report-hermes","stars":3},{"name":"eps1lon/poe-mods","stars":2},{"name":"eps1lon/TreeStats","stars":2},{"name":"eps1lon/poe-react-item","stars":2},{"name":"eps1lon/aria-activedescendant-static-dynamic","stars":2},{"name":"eps1lon/eslint-focus","stars":2},{"name":"eps1lon/poe-i18n","stars":1},{"name":"eps1lon/berry-sapper","stars":1},{"name":"eps1lon/mui-workflow-maintenance","stars":1},{"name":"eps1lon/vax-notify","stars":1},{"name":"eps1lon/crowdin-prettier","stars":0},{"name":"eps1lon/azure-pipelines-source-version","stars":0},{"name":"eps1lon/mui-types-perf","stars":0},{"name":"eps1lon/testing-library-envinfo","stars":0},{"name":"eps1lon/mui-maintainer-dashboard-remix","stars":0}],"totalStars":1662026,"updatedAt":"2023-03-08T10:01:01.421Z"}