{"repositories":[{"name":"jsdom/jsdom","stars":15962},{"name":"DefinitelyTyped/DefinitelyTyped","stars":34481},{"name":"facebook/react","stars":170228},{"name":"kentcdodds/kentcdodds.com","stars":659},{"name":"facebook/jest","stars":35518},{"name":"w3c/aria","stars":407},{"name":"fkling/astexplorer","stars":3953},{"name":"mui-org/material-ui","stars":68938},{"name":"cssinjs/jss","stars":6386},{"name":"babel/website","stars":644},{"name":"nodejs/node","stars":79966},{"name":"benmosher/eslint-plugin-import","stars":3340},{"name":"dequelabs/axe-core","stars":3941},{"name":"reduxjs/react-redux","stars":21084},{"name":"circleci/circleci-docs","stars":528},{"name":"jsx-eslint/eslint-plugin-jsx-a11y","stars":2420},{"name":"popperjs/popper-core","stars":17526},{"name":"webpack/webpack.js.org","stars":1993},{"name":"vercel/next.js","stars":69653},{"name":"reactjs/react-transition-group","stars":8496},{"name":"codesandbox/codesandbox-client","stars":10662},{"name":"A11yance/aria-query","stars":136},{"name":"emotion-js/emotion","stars":13214},{"name":"dperini/nwsapi","stars":31},{"name":"kentcdodds/kcd-scripts","stars":743},{"name":"reactjs/reactjs.org","stars":5628},{"name":"mui-org/material-ui-pickers","stars":2237},{"name":"testing-library/react-testing-library","stars":14645},{"name":"tensorflow/tfjs-models","stars":9266},{"name":"testing-library/dom-testing-library","stars":2590},{"name":"typescript-cheatsheets/react","stars":25997},{"name":"testing-library/testing-library-docs","stars":303},{"name":"microsoft/TypeScript-Website","stars":1012},{"name":"yarnplugins/yarn-plugin-deduplicate","stars":3},{"name":"shrutikapoor08/blogs","stars":18},{"name":"microsoft/DefinitelyTyped-tools","stars":73},{"name":"mdn/content","stars":2731}],"totalStars":635412,"updatedAt":"2021-06-21T16:48:58.758Z"}